LICENSE
MANIFEST.in
requirements.txt
setup.cfg
setup.py
datahandling/VERSION
datahandling/__init__.py
datahandling/datahandling.py
datahandling/widgetmultiplot.py
datahandling.egg-info/PKG-INFO
datahandling.egg-info/SOURCES.txt
datahandling.egg-info/dependency_links.txt
datahandling.egg-info/requires.txt
datahandling.egg-info/top_level.txt
datahandling/LeCroy/LeCroy.py
datahandling/LeCroy/__init__.py
datahandling/Saleae/Saleae.py
datahandling/Saleae/__init__.py
datahandling/sim_data/__init__.py
datahandling/sim_data/sim_data.py
datahandling/thermo/__init__.py
datahandling/thermo/thermo.py