Metadata-Version: 1.1
Name: datahandling
Version: 3.2.7
Summary: Python package with functions for data analysis
Home-page: https://github.com/AshleySetter/datahandling
Author: Ashley Setter
Author-email: A.Setter@soton.ac.uk
License: UNKNOWN
Download-URL: https://github.com/AshleySetter/datahandling/archive/3.2.7.tar.gz
Platform: UNKNOWN
